climate_resilience/__init__.py
climate_resilience/bias_correction.py
climate_resilience/constants.py
climate_resilience/downloader.py
climate_resilience/eeanalysis.py
climate_resilience/gribanalysis.py
climate_resilience/preprocess.py
climate_resilience/utils.py
climate_resilience/visualize.py
climate_resilience-0.4.10.dist-info/LICENSE
climate_resilience-0.4.10.dist-info/METADATA
climate_resilience-0.4.10.dist-info/WHEEL
climate_resilience-0.4.10.dist-info/top_level.txt
climate_resilience-0.4.10.dist-info/RECORD
