Metadata-Version: 2.1
Name: climate-resilience
Version: 0.4.10
Summary: Download, Preprocessing, and Visualization code for climate resilience data.
Home-page: https://github.com/ALTEMIS-DOE/climate-resilience.git
Author: Satyarth Praveen, Zexuan Xu, Haruko Wainwright
Author-email: satyarth@lbl.gov, zexuanxu@lbl.gov, hmwainwright@lbl.gov
Project-URL: Bug Tracker, https://github.com/ALTEMIS-DOE/climate-resilience/issues
Project-URL: Documentation, https://climate-resilience.readthedocs.io/
Project-URL: Source, https://github.com/ALTEMIS-DOE/climate-resilience
Classifier: Programming Language :: Python :: 3
Classifier: License :: OSI Approved :: MIT License
Classifier: Operating System :: OS Independent
Requires-Python: >=3.6
License-File: LICENSE
Requires-Dist: numpy
Requires-Dist: pandas
Requires-Dist: seaborn
Requires-Dist: matplotlib
Requires-Dist: leafmap
Requires-Dist: ipyleaflet
Requires-Dist: tqdm
Requires-Dist: geopandas
Requires-Dist: earthengine-api
Requires-Dist: eecmip5
Requires-Dist: joblib
Requires-Dist: scikit-downscale
Requires-Dist: probscale
